homework_docker/__init__.py
homework_docker/main.py
tools_part_2_nmzgnv-0.0.1.dist-info/LICENSE
tools_part_2_nmzgnv-0.0.1.dist-info/METADATA
tools_part_2_nmzgnv-0.0.1.dist-info/WHEEL
tools_part_2_nmzgnv-0.0.1.dist-info/RECORD
