Metadata-Version: 2.1
Name: tools-part-2-nmzgnv
Version: 0.0.1
Summary: A Tinkoff Python AB hw-2 package
License: MIT
Author: nmzgnv
Author-email: nick-mozg1@mail.ru
Requires-Python: >=3.10,<4.0
Classifier: License :: OSI Approved :: MIT License
Classifier: Programming Language :: Python :: 3
Classifier: Programming Language :: Python :: 3.10
Classifier: Programming Language :: Python :: 3.11
Requires-Dist: httpx (>=0.25.0,<0.26.0)
